quant_friend/__init__.py
quant_friend/__version__.py
quant_friend/api.py
quant_friend/hosts.py
quant_friend/notice.py
quant_friend/ucloud.py
quant_friend-0.0.1.dist-info/METADATA
quant_friend-0.0.1.dist-info/WHEEL
quant_friend-0.0.1.dist-info/top_level.txt
quant_friend-0.0.1.dist-info/RECORD
