Metadata-Version: 2.1
Name: quant-friend
Version: 0.0.1
Summary: quant helper.
Home-page: https://github.com/caijiang/quant-friend
Author: Cai Jiang
Author-email: luffy.ja@gmail.com
License: MIT
Platform: UNKNOWN
Classifier: License :: OSI Approved :: MIT License
Classifier: Programming Language :: Python
Classifier: Programming Language :: Python :: 3
Classifier: Programming Language :: Python :: 3.6
Classifier: Programming Language :: Python :: Implementation :: CPython
Classifier: Programming Language :: Python :: Implementation :: PyPy
Requires-Python: >=3.6.0
Requires-Dist: ucloud-sdk-python3
Requires-Dist: ucloud
